Workbook
Name \z: #REF!
Name \z: #REF!
Name \z: #REF!
Name \z: #REF!
Name _1W_一: #REF!,#REF!,#REF!,#REF!
Name _1W_一: #REF!,#REF!,#REF!,#REF!
Name _1W_一: #REF!,#REF!,#REF!,#REF!
Name _1W_一: #REF!,#REF!,#REF!,#REF!
Name A: #REF!
Name A: #REF!
Name A: #REF!
Name A: #REF!
Name Cl2入力: [1]Cl2!$C$8:$C$9,[1]Cl2!$F$9:$F$14,[1]Cl2!$H$9:$H$14,[1]Cl2!$C$7
Name d: #REF!
Name d: #REF!
Name d: #REF!
Name d: #REF!
Name FLOW: #REF!
Name FLOW: #REF!
Name HCl入力: [1]HCl!$C$8:$C$9,[1]HCl!$F$9:$F$14,[1]HCl!$H$9:$H$14,[1]HCl!$C$7
Name Limit: #REF!
Name Limit: #REF!
Name Limit: #REF!
Name Limit: #REF!
Name NH3入力: [2]NH3!$C$8:$C$9,[2]NH3!$F$9:$F$14,[2]NH3!$H$9:$H$14,[2]NH3!$C$7
Name Pa: #REF!
Name Pa: #REF!
Name Pa: #REF!
Name Pa: #REF!
Name PDS入力: [1]PDS!$C$8:$C$9,[1]PDS!$F$9:$F$14,[1]PDS!$H$9:$H$14,[1]PDS!$C$7
Name Po: #REF!
Name Po: #REF!
Name Po: #REF!
Name Po: #REF!
Name Print_Area_MI: #REF!
Name Print_Area_MI: #REF!
Name Print_Area_MI: #REF!
Name Print_Area_MI: #REF!
Name Ps: #REF!
Name Ps: #REF!
Name Ps: #REF!
Name Ps: #REF!
Name Ｐv: #REF!
Name Ｐv: #REF!
Name Ｐv: #REF!
Name Ｐv: #REF!
Name Request: #REF!
Name Request: #REF!
Name S0x50入力: '[1]SOx 50'!$C$8:$C$9,'[1]SOx 50'!$C$12,'[1]SOx 50'!$F$9:$F$14,'[1]SOx 50'!$H$9:$H$14,'[1]SOx 50'!$C$7
Name SOx入力: '[1]SOx 10'!$C$8:$C$9,'[1]SOx 10'!$C$12,'[1]SOx 10'!$F$9:$F$14,'[1]SOx 10'!$H$9:$H$14,'[1]SOx 10'!$C$7
Name ｔ: #REF!
Name ｔ: #REF!
Name ｔ: #REF!
Name ｔ: #REF!
Name To: #REF!
Name To: #REF!
Name To: #REF!
Name To: #REF!
Name Xw: #REF!
Name Xw: #REF!

Sheet 1.Service Contraction
A1: CÔNG TY TNHH CHUGAI TECHNOS VIỆT NAM | F1: CỘNG HÒA XÃ HỘI CHỦ NGHĨA VIỆT NAM
F2: Độc lập - Tự do - Hạnh phúc
A5: HỢP ĐỒNG DỊCH VỤ
C7: Số hợp đồng: | E7: ="CCTVN - "&Q7&"-"&S7&U7&"-"&O7 -> CCTVN - DAV-201704-01 | N7: No．： | O7: 01 | P7: Customer： | Q7: DAV | R7: Year： | S7: 2017 | T7: Month： | U7: 04
A9: - Căn cứ luật dân sự số 33/2005/QH11 do Quốc Hội ban hành ngày 14 tháng 6 năm 2005. - Căn cứ luật thương mại số 36/2005/QH11 do Quốc Hội ban hành ngày 14 tháng 6 năm 2005.
A14: －Dựa trên nhu cầu và khả năng của cả hai bên.
A15: Hợp đồng này được làm vào ngày 18 tháng 04 năm 2017 giữa hai bên | N15: Contract date： | P15: 18-Apr-17
A17: Bên A | C17: ： | D17: CÔNG TY TNHH VẬT LIỆU MỚI DENKA VIỆT NAM | N17: Party A | P17: DENKA ADVANCED MATERIALS VIETNAM CO.,LTD
A18: Người đại diện | C18: ： | D18: Ông YOSHIO SASAKI | N18: Represented by | P18: MR．YOSHIO SASAKI
A19: Chức vụ | C19: ： | D19: Tổng giám đốc | N19: Title | P19: General Director
A20: Địa chỉ | C20: ： | D20: Lô D-5, Khu công nghiệp Thăng Long II, Xã Liêu Xá 3, Huyện Yên Mỹ, Tỉnh Hưng Yên, Việt Nam | N20: Address | P20: Plot D-5, Thang Long Industrial Park II, Lieu Xa Commune 3, Yen My District, Hung Yen Province, Vietnam
A22: Điện thoại | C22: ： | D22: +84-221-3974-805 | N22: Teｌ | P22: +84-221-3974-805
A23: Fax | C23: ： | D23: =P23 -> +84-221-3974-806 | N23: Fax | P23: +84-221-3974-806
A24: Mã số thuế | C24: ： | D24: =P24 -> 0900870366 | N24: Tax code | P24: 0900870366
A25: Trên đây gọi là bên A
A27: Bên B | C27: ： | D27: CÔNG TY TNHH CHUGAI TECHNOS VIỆT NAM
A28: Người đại diện | C28: ： | D28: Ông MASAMI OUE
A29: Chức vụ | C29: ： | D29: Tổng giám đốc
A30: Địa chỉ | C30: ： | D30: 66 Cao Triều Phát, khu phố Hưng Gia 4, Phường Tân Phong, Quận 7, Tp.HCM, Việt Nam | N30: Table-1 Acc number
N31: No. | O31: currency | P31: Acc Number | Q31: currency
A32: Điện thoại | C32: ： | D32: +84-8-5410-9111 | N32: 1 | O32: USD | P32: 10065701 | Q32: US Dollar
A33: Fax | C33: ： | D33: +84-8-5410-9222 | N33: 2 | O33: VND | P33: 10065702 | Q33: Vietnamese Dong
A34: Mã số thuế | C34: ： | D34: 0312737198 | N34: 3 | O34: JPY | P34: 10065703 | Q34: Japanese Yen
A35: Chủ tài khoản | D35: CÔNG TY TNHH CHUGAI TECHNOS VIỆT NAM
A36: Số tài khoản | D36: =IF(O41="","",VLOOKUP(O41,N32:P34,3,TRUE)) -> 10065702 | E36: VNĐ
A37: Ngân hàng | D37: Sumitomo Mitsui Banking Corporation － Ho Chi Minh Branch
A38: Trên đây gọi là bên B
A40: Hai bên đã đồng ý ký hợp đồng với các điều khoản và điều kiện sau đây: | N40: Acc number (Choose from Table-1)
N41: Currency | O41: 2
A42: ĐIỀU I: DỊCH VỤ
A44: 1．1 | B44: Bên B đồng ý cung cấp cho Bên A dịch vụ sau. | N44: Table-2 Acc number
B45: Tên dịch vụ | D45: ： | E45: Kiểm tra PT mối hàn của thùng chứa | N45: No. | O45: Service | S45: Cost
B46: Địa điểm | D46: ： | E46: CÔNG TY TNHH VẬT LIỆU MỚI DENKA VIỆT NAM | N46: 1 | O46: Analysis | S46: The above contract value includes direct labor, direct, company cost and so on.
B47: Quốc gia | D47: ： | E47: Việt Nam | N47: 2 | O47: Environmental consulting | S47: The above contract value is full-package price, including direct labor, direct, consalting, company cost and so on.
B48: Thời gian | D48: ： | E48: Từ | F48: 24/04/2017 | G48: Đến | H48: 11/05/2017 | N48: 3 | O48: Non-destructive inspection | S48: The above contract value is full-package price, including direct labor, direct , inspection, company cost and so on.
B49: Ngày | D49: ： | E49: 18 ngày
N50: Service subject line | Q50: ： | R50: PT Inspection for container welding lines
A51: 1．2 | B51: Tất cả các dịch vụ do Bên B cung cấp được liệt kê trong báo giá kèm theo là một phần không thể tách rời của hợp đồng này. | N51: Relevant facilities | Q51: ： | R51: -
N52: Site | Q52: ： | R52: DENKA ADVANCED MATERIALS VIETNAM CO.,LTD
B53: Số báo giá | D53: ='2.Quotation Service Order'!N14 -> QCTVN201704-01 | N53: Country | Q53: ： | R53: Vietnam
A55: ĐIỀU II: GIÁ TRỊ HỢP ĐỒNG
A56: 2．1 | B56: 103,600,000 VNĐ
B57: (Bằng chữ: Một trăm lẻ ba triệu sáu trăm nghìn đồng) | N57: This service will be carried out only in Japan. The data of service will be used only in Japan. It will not be used in Vietnam.
N59: Relevant month quotation
A60: 2．2 | B60: Giá trị hợp đồng trên bao gồm chi phí nhân công, chi phí trực tiếp. | N60: No．： | O60: 01 | P60: Year： | Q60: 2016 | R60: Month： | S60: 02
B61: Thuế được loại trừ khỏi giá trị hợp đồng. Nếu bên A có bất kỳ ưu đãi thuế nào, bên A phải chứng minh cho bên B để thanh toán tiền thuế.
A64: 2．3 | B64: Giá trên được tính dựa trên điều kiện hiện tại. Sau khi kiểm tra tình trạng cuối cùng, nếu có bất kỳ chi phí phát sinh sẽ được thảo luận với quý công ty. | N64: Price | O64: =TEXT(#REF!,"#,###") -> #REF! | P64: =E36 -> VNĐ
A67: ĐIỀU III: PHƯƠNG THỨC THANH TOÁN
N68: Vietnamese Dong | O68: One Hundred Three | Q68: Million
A69: Thanh toán bằng chuyển khoản ngân hàng Việt Nam đồng như sau: | O69: Six | Q69: Hundred
Q70: Thousand
A71: 3．1 | B71: 100% tổng giá trị hợp đồng sẽ được thanh toán vào trước cuối tháng tiếp theo bằng chuyển khoản ngân hàng sau khi bên A nhận được báo cáo.
A74: 3．2 | B74: Trong trường hợp thanh toán trễ, bên A phải chịu phạt theo lãi suất của ngân hàng Sumitomo Mitsui Banking Vietnam và thời gian chờ thanh toán chậm.
A77: ĐIỀU IV: BẢO HÀNH
A79: 4．1 | B79: Trong trường hợp có sự thay đổi thời gian thực hiện dịch vụ, Bên A sẽ liên hệ trực tiếp với Bên B bằng điện thoại: (+ 84-8-5410-9111) hoặc bằng Fax: (84-8-5410-9222) sớm nhất có thể. Bên B có trách nhiệm giải quyết vấn đề nhanh nhất có thể.
N81: VAT | O81: 1 | P81: applicable | Q81: This Price is 10% VAT applicable. | U81: It includes VAT.
O82: 2 | P82: not applicable | Q82: This Price is not 10% VAT applicable.
A83: ĐIỀU V: TRÁCH NHIỆM CỦA MỖI BÊN | N83: Choice | O83: 1 | P83: =IF(O83="","",VLOOKUP(O83,O81:Q82,3,TRUE)) -> This Price is 10% VAT applicable.
A85: Trách nhiệm của mỗi bên được diễn tả dưới đây:
M86: 100% of total contract value shall be paid by the end of the next month when receiving a handing over and payment request.
A87: BÊN A：Chịu trách nhiệm: | M87: 50% of total Contract value shall be paid immediately upon quotation's approval. 50% of total Contract value shall be paid in 7days time after the two parties has signed the works checking minute and receipt of the payment request and the official tax invoice.
A88: - | B88: Bên A phải nêu rõ yêu cầu bên A cho bên B trước khi ký hợp đồng.
A89: - | B89: Bên A sẽ hợp tác với bên B trong quá trình kiểm tra dịch vụ.
A90: - | B90: Bên A và Bên B không được phép tiết lộ thông tin bí mật cho bên thứ ba (bao gồm tất cả các nội dung của hợp đồng này) trong quá trình ký kết và thực hiện hợp đồng, trước và sau khi chấm dứt hoặc hết hạn hợp đồng.
A94: BÊN B： Chịu trách nhiệm:
A95: - | B95: Kiểm tra PT của bể chứa lò hơi V921A, kiểm tra ăn mòn và phá hủy
A96: - | B96: Bàn giao bản báo cáo kiểm tra
A97: - | B97: Bên A và Bên B không được phép tiết lộ thông tin bí mật cho bên thứ ba (bao gồm tất cả các nội dung của hợp đồng này) trong quá trình ký kết và thực hiện hợp đồng, trước và sau khi chấm dứt hoặc hết hạn hợp đồng.
A101: ĐIỀU VI: KẾT THÚC DỊCH VỤ
A103: 6．1 | B103: Bên A phải thông báo cho Bên B ngày kết thúc dịch vụ trước khi kết thúc.
A104: 6．2 | B104: Bên B phải cung cấp cho Bên A biên bản bàn giao sau khi dịch vụ kết thúc.
A106: ĐIỀU VII: THÔNG BÁO ĐỊA CHỈ
A108: Mọi thông báo giữa hai bên sẽ được gửi đến các địa chỉ sau:
A110: Bên A： | B110: CÔNG TY TNHH VẬT LIỆU MỚI DENKA VIỆT NAM
A111: Người nhận： | C111: Ông YOSHIO SASAKI | F111: =P22 -> +84-221-3974-805
A113: Party B： | B113: CHUGAI TECHNOS VIETNAM COMPANY LIMITED
A114: Người nhận ： | C114: =D28 -> Ông MASAMI OUE | F114: =D32 -> +84-8-5410-9111
A118: ĐIỀU VIII: GIẢI QUYẾT TRANH CHẤP | N118: Period for acceptance inquiries： | Q118: 10 days
A120: 8．1 | B120: Hai bên phải thông báo cho nhau về tiến độ công việc. Bất kỳ vấn đề phát sinh từ thỏa thuận này sẽ được ưu tiên giải quyết bằng cách thảo luận theo cách thức hợp tác. Đơn phương chấm dứt hợp đồng sẽ không được chấp nhận.
A124: 8．2 | B124: Trong trường hợp không giải quyết được tranh chấp giữa hai bên thì Trung Tâm Trọng Tài Quốc Tế Việt Nam thuộc Phòng Thương Mại và Công nghiệp Việt Nam giải quyết. | N124: Party A ： | O124: Mr. Hirohiko Muraoka
O125: +81-82-295-2237
A127: 8．3 | B127: Nếu tranh chấp không thể giải quyết bởi trọng tài thì bên A hoặc bên B hoặc cả hai bên có thể yêu cầu Toà kinh tế tại thành phố Hồ Chí Minh xem xét và giải quyết các tranh chấp đó và quyết định của Toà án là cuối cùng và ràng buộc đối với cả hai bên.
N128: Party B ： | O128: Mr. Masami Oue
A132: ĐIỀU IX: ĐIỀU KIỆN CHUNG
A134: 9．1 | B134: Hai bên đồng ý thực hiện đầy đủ các điều khoản và điều kiện quy định trong hợp đồng này. Mọi thay đổi đối với hợp đồng này phải được sự đồng ý và bổ sung bằng văn bản có chữ ký hợp lệ của người đại diện có thẩm quyền của cả hai bên.
A138: 9．2 | B138: Hợp đồng này được làm thành 02 bản gốc bằng tiếng Anh và 02 bản gốc bằng tiếng Việt, tất cả các bản tiếng Anh đều được ưu tiên. Mỗi bên giữ 01 bản bằng tiếng Anh và 01 bản tiếng Việt.
B141: Trong trường hợp có sự khác biệt giữa bản tiếng Việt và tiếng Anh, phiên bản tiếng Anh sẽ được sử dụng làm cơ sở để giải thích và tham khảo.
A144: BÊN A | G144: BÊN B
A145: CÔNG TY TNHH VẬT LIỆU MỚI DENKA VIỆT NAM | G145: =D27 -> CÔNG TY TNHH CHUGAI TECHNOS VIỆT NAM
A151: =D18 -> Ông YOSHIO SASAKI | G151: =D28 -> Ông MASAMI OUE

Sheet 2.Quotation Service Order
D2: CÔNG TY TNHH CHUGAI TECHNOS VIỆT NAM
E3: 66 Cao Triều Phát, Khu phố Hưng Gia 4, Phường Tân Phong, Quận 7, Tp.HCM
E6: Điện thoại：08-5410-9111 ； Fax：08-5410-9222
F8: Website： | H8: http://www.chugai-tec-vn.com/jp
A9: BÁO GIÁ DỊCH VỤ
A13: Ngày： | B13: 18/04/2017 | L13: Date： | N13: 42843
A14: Số： | B14: =N14 -> QCTVN201704-01 | L14: Quotation： | N14: QCTVN201704-01
A16: Công ty： | B16: CÔNG TY TNHH VẬT LIỆU MỚI DENKA VIỆT NAM | L16: To： | N16: ='[5]1.Service Contraction'!P17 -> DENKA ADVANCED MATERIALS VIETNAM CO.,LTD.
A18: Địa chỉ： | B18: Lô D-5, Khu Công Nghiệp Thăng Long II, Xã Liêu Xá 3, Huyện Yên Mỹ, Tỉnh Hưng Yên, Việt Nam | L18: Add： | N18: ='[5]1.Service Contraction'!P20 -> Plot D-5, Thang Long Industrial Park ⅡYen my District, Hung Yen Province, Vietnam
A20: Điện thoại： | B20: +84-221-3974-805 | L20: Tel ： | N20: ='C:\Users\DELL\Documents\Company Job\Denka\[Quotation Denka (Vietnamese).xlsx]1.Service Contraction'!P21
A21: Fax： | B21: +84-221-3974-806 | L21: Fax： | N21: ='C:\Users\DELL\Documents\Company Job\Denka\[Quotation Denka (Vietnamese).xlsx]1.Service Contraction'!P22
A23: Kính gửi quý công ty, chúng tôi xin gửi báo giá như sau:
A25: Dịch vụ: | B25: Kiểm tra PT mối hàn của thùng chứa | G25: Tổng giá: | H25: ='[5]3.Detail Quotation'!J52 -> 103600000 | M25: ='[5]1.Service Contraction'!R49 -> PT Inspection for container welding lines
B26: 1 | C26: Chi phí nhân công | G26: ='[5]3.Detail Quotation'!J19 -> 86000000
B27: 2 | C27: Chi phí | G27: ='[5]3.Detail Quotation'!J26 -> 17600000
D28: Tổng cộng: | G28: ='[5]3.Detail Quotation'!J50 -> 103600000
C30: Giá trên không bao gồm 10% VAT
A32: Điều kiện:
A33: － | B33: Hiệu lực： | D33: 90 ngày
A34: － | B34: Thời gian： | D34: Từ | E34: 42849 | F34: Đến | G34: 11/5/2017 | I34: 18 | J34: Ngày
A35: － | B35: Giá dịch vụ： | D35: Giá trên căn cứ vào điều kiện hiện tại. Sau khi kiểm tra điều kiện cuối cùng. Nếu có bất kỳ chi phí phát sinh sẽ được thảo luận cùng quý công ty.
A38: － | B38: Nội dung： | D38: Kiểm tra PT của bể chứa lò hơi V921A, kiểm tra ăn mòn và phá hủy
A39: － | B39: Sản phẩm： | D39: Bản báo cáo kiểm tra
A40: － | B40: Thanh toán： | D40: 100 % giá trị hợp đồng sẽ được thanh toán trước cuối tháng tiếp theo bằng chuyển khoản sau khi bên A nhận được báo cáo.
A44: CÔNG TY TNHH VẬT LIỆU MỚI DENKA VIỆT NAM | G44: =D2 -> CÔNG TY TNHH CHUGAI TECHNOS VIỆT NAM
A46: Ngày： | B46: =N13 -> 42843 | G46: Ngày： | H46: =N13 -> 42843
B53: Chữ ký và đóng dấu công ty | H53: Chữ ký và đóng dấu công ty

Sheet 3.Detail Quotation
B2: CHI TIẾT BÁO GIÁ | Z2: 御 見 積 書
G3: Ngày: | I3: ='[5]2.Quotation Service Order'!N13 -> 42843 | AG3: =TODAY() -> 42870
G4: Số báo giá: | I4: ='[5]2.Quotation Service Order'!N14 -> QCTVN201704-01
B5: CÔNG TY TNHH VẬT LIỆU MỚI DENKA VIỆT NAM | G5: CÔNG TY TNHH CHUGAI TECHNOS VIỆT NAM | Z5: 日本プラントメーカー 御中 | AF5: CHUGAI TECHNOS VIETNAM CO.,LTD | AK5: CHUGAI TECHNOS VIETNAM CO.,LTD
B6: Dịch vụ: | C6: ='[5]2.Quotation Service Order'!B25 -> Kiểm tra PT mối hàn của thùng chứa | G6: =J12 -> Ông Masami Oue | AA6: ジャカルタボイラ性能試験 | AE6: 社長 大 上 政 視
H7: 66 Cao Triều Phát, Khu phố Hưng Gia 4, Phường Tân Phong, Quận 7, Tp.HCM , Việt Nam | Z7: 件 名
B8: ='[5]2.Quotation Service Order'!A23 -> Kính gửi quý công ty, chúng tôi xin gửi báo giá như sau: | M8: USD/VND= | N8: 23000 | Z8: 首題の件に関し下記の通り御見積申し上げます | AF8: 66 Cao Trieu Phat, Hung Gia 4 area,
AF9: Tan Phong ward, District 7, Ho Chi Minh city.
B10: =J52 -> 103600000 | F10: Điện thoại: +84-8-5410-9111 Fax: +84-8-5410-9222 | P10: B．Overtime Money | Z10: =AH52 -> 2988700 | AE10: TEL +84-0-0000-0000 FAX +84-0-000-000
B11: Địa điểm： | C11: Việt Nam | V11: Currency：JPY | Z11: 場 所 | AA11: インドネシア･ジャカルタ
B12: Hiệu lực： | C12: 90 ngày | G12: Phụ trách báo giá： | J12: Ông Masami Oue | P12: Total salary | Q12: Basic unit price(A) | R12: Weekday | T12: Holiday(Sat and Sun） | V12: Public holiday | Z12: 有効期間 | AE12: 見積責任者：
R13: Day | S13: Midnight | T13: Day | U13: Midnight | V13: Day | W13: Midnight
B14: Mục | E14: Nội dung | G14: Số lượng | H14: Đơn vị | I14: Đơn giá (VNĐ) | J14: Giá (VNĐ) | M14: Unit price(USD) | N14: Price(USD) | P14: 35000 | Q14: =P14/22/8 -> 198.86364 | R14: =Q14*1.5 -> 298.29545 | S14: =Q14*1.5+Q14*0.3+Q14*0.2 -> 397.72727 | T14: =Q14*2 -> 397.72727 | U14: =Q14*2+Q14*0.3+Q14*2*0.2 -> 536.93182 | V14: =Q14*3 -> 596.59091 | W14: =Q14*3+Q14*0.3+Q14*3*0.2 -> 775.56818 | Z14: 項 目 | AA14: 内 容 | AE14: 数 量 | AF14: 単 位 | AG14: 単 価 | AH14: 金 額
B15: 1. | C15: Chi phí nhân công | G15: 1 | H15: Đơn vị | I15: 86000000 | J15: =IF(COUNT(G15:I15)=0,"",G15*I15) -> 86000000 | P15: 45000 | Q15: =P15/22/8 -> 255.68182 | R15: =Q15*1.5 -> 383.52273 | S15: =Q15*1.5+Q15*0.3+Q15*0.2 -> 511.36364 | T15: =Q15*2 -> 511.36364 | U15: =Q15*2+Q15*0.3+Q15*2*0.2 -> 690.34091 | V15: =Q15*3 -> 767.04545 | W15: =Q15*3+Q15*0.3+Q15*3*0.2 -> 997.15909 | Z15: １．直接人件費 | AK15: Ｂ．ベトナム法による残業代
C16: (1) | D16: Chuẩn bị và dọn dẹp | I16: =IF(COUNT(G16)=0,"",M16*$N$8) | J16: =IF(COUNT(G16:I16)=0,"",G16*I16) | P16: 100000 | Q16: =P16/22/8 -> 568.18182 | R16: =Q16*1.5 -> 852.27273 | S16: =Q16*1.5+Q16*0.3+Q16*0.2 -> 1136.3636 | T16: =Q16*2 -> 1136.3636 | U16: =Q16*2+Q16*0.3+Q16*2*0.2 -> 1534.0909 | V16: =Q16*3 -> 1704.5455 | W16: =Q16*3+Q16*0.3+Q16*3*0.2 -> 2215.9091 | AA16: （２） | AB16: 機材準備及び整備 | AE16: 6 | AF16: 人･日 | AG16: 25000 | AH16: =IF(COUNT(AE16:AG16)=0,"",AE16*AG16) -> 150000 | AK16: 基本給 | AL16: 基本単価 （Ａ） | AM16: 平日 | AO16: 休日(土日） | AQ16: 祝祭日
C17: (2) | D17: Điều tra ngoài công trường 1 kỹ sư cho 4 ngày bao gồm ngày di chuyển | I17: =IF(COUNT(G17)=0,"",M17*$N$8) | J17: =IF(COUNT(G17:I17)=0,"",G17*I17) | P17: 120000 | Q17: =P17/22/8 -> 681.81818 | R17: =Q17*1.5 -> 1022.7273 | S17: =Q17*1.5+Q17*0.3+Q17*0.2 -> 1363.6364 | T17: =Q17*2 -> 1363.6364 | U17: =Q17*2+Q17*0.3+Q17*2*0.2 -> 1840.9091 | V17: =Q17*3 -> 2045.4545 | W17: =Q17*3+Q17*0.3+Q17*3*0.2 -> 2659.0909 | AA17: （３） | AB17: 通関手続き | AE17: 4 | AF17: 人･日 | AG17: 25000 | AH17: =IF(COUNT(AE17:AG17)=0,"",AE17*AG17) -> 100000 | AM17: 通常 | AN17: 深夜 | AO17: 通常 | AP17: 深夜 | AQ17: 通常 | AR17: 深夜
C18: (3) | D18: Báo cáo | I18: =IF(COUNT(G18)=0,"",M18*$N$8) | J18: =IF(COUNT(G18:I18)=0,"",G18*I18) | P18: ※Ａ＝Basic Salary／22days／8 hours | AA18: （４） | AB18: 報告書作成（社内） | AE18: 2 | AF18: 人･日 | AG18: 25000 | AH18: =IF(COUNT(AE18:AG18)=0,"",AE18*AG18) -> 50000 | AK18: 30000 | AL18: =AK18/22/8 -> 170.45455 | AM18: =AL18*1.5 -> 255.68182 | AN18: =AL18*1.5*1.3+AL18*0.2 -> 366.47727 | AO18: =AL18*2 -> 340.90909 | AP18: =AL18*2*1.3+AL18*2*0.2 -> 511.36364 | AQ18: =AL18*3 -> 511.36364 | AR18: =AL18*3*1.3+AL18*3*0.2 -> 767.04545
D19: Tổng | I19: =IF(COUNT(G19)=0,"",M19*$N$8) | J19: =J15 -> 86000000 | P19: Midnight Overtime is between p.m 21:00 and a.m 5:00 | AA19: （５） | AB19: 現地作業 | AK19: 50000 | AL19: =AK19/22/8 -> 284.09091 | AM19: =AL19*1.5 -> 426.13636 | AN19: =AL19*1.5*1.3+AL19*0.2 -> 610.79545 | AO19: =AL19*2 -> 568.18182 | AP19: =AL19*2*1.3+AL19*2*0.2 -> 852.27273 | AQ19: =AL19*3 -> 852.27273 | AR19: =AL19*3*1.3+AL19*3*0.2 -> 1278.4091
I20: =IF(COUNT(G20)=0,"",M20*$N$8) | J20: =IF(COUNT(G20:I20)=0,"",G20*I20) | AB20: ①技術員 | AE20: 24 | AF20: 人･日 | AG20: 26000 | AH20: =IF(COUNT(AE20:AG20)=0,"",AE20*AG20) -> 624000 | AK20: 70000 | AL20: =AK20/22/8 -> 397.72727 | AM20: =AL20*1.5 -> 596.59091 | AN20: =AL20*1.5*1.3+AL20*0.2 -> 855.11364 | AO20: =AL20*2 -> 795.45455 | AP20: =AL20*2*1.3+AL20*2*0.2 -> 1193.1818 | AQ20: =AL20*3 -> 1193.1818 | AR20: =AL20*3*1.3+AL20*3*0.2 -> 1789.7727
B21: 2. | C21: Chi phí | G21: 1 | H21: Đơn vị | I21: 17600000 | J21: =I21 -> 17600000 | AB21: ② 〃 時間外、休日 | AE21: 9 | AF21: 人･Hr | AG21: 4000 | AH21: =IF(COUNT(AE21:AG21)=0,"",AE21*AG21) -> 36000 | AK21: 100000 | AL21: =AK21/22/8 -> 568.18182 | AM21: =AL21*1.5 -> 852.27273 | AN21: =AL21*1.5*1.3+AL21*0.2 -> 1221.5909 | AO21: =AL21*2 -> 1136.3636 | AP21: =AL21*2*1.3+AL21*2*0.2 -> 1704.5455 | AQ21: =AL21*3 -> 1704.5455 | AR21: =AL21*3*1.3+AL21*3*0.2 -> 2556.8182
C22: (1) | D22: Chi phí di chuyển | I22: =IF(COUNT(G22)=0,"",M22*$N$8) | J22: =IF(COUNT(G22:I22)=0,"",G22*I22) | AB22: ③主任技師(日本人） | AE22: 8 | AF22: 人･日 | AG22: 40000 | AH22: =IF(COUNT(AE22:AG22)=0,"",AE22*AG22) -> 320000 | AK22: 120000 | AL22: =AK22/22/8 -> 681.81818 | AM22: =AL22*1.5 -> 1022.7273 | AN22: =AL22*1.5*1.3+AL22*0.2 -> 1465.9091 | AO22: =AL22*2 -> 1363.6364 | AP22: =AL22*2*1.3+AL22*2*0.2 -> 2045.4545 | AQ22: =AL22*3 -> 2045.4545 | AR22: =AL22*3*1.3+AL22*3*0.2 -> 3068.1818
C23: (2) | D23: Khách sạn | I23: =IF(COUNT(G23)=0,"",M23*$N$8) | J23: =IF(COUNT(G23:I23)=0,"",G23*I23) | AB23: ④ 〃 時間外、休日 | AE23: 3 | AF23: 人･Hr | AG23: 6250 | AH23: =IF(COUNT(AE23:AG23)=0,"",AE23*AG23) -> 18750 | AK23: ※Ａ＝基本給／22日／８ｈｒ
C24: (3) | D24: Trợ cấp công tác | AA24: 小計 | AH24: =SUM(AH16:AH23) -> 1298750 | AK24: ※深夜とは、22時～６時。
C25: (4) | D25: Chi phí thiết bị | N25: =IF(COUNT(G25)=0,"",G25*M25)
D26: Tổng | J26: =J21 -> 17600000 | N26: =IF(COUNT(G26)=0,"",G26*M26) | Z26: ２．直接経費
N27: =IF(COUNT(G27)=0,"",G27*M27) | AA27: （１） | AB27: 交通費 | AE27: 一 | AF27: 式 | AH27: 238000
N28: =IF(COUNT(G28)=0,"",G28*M28) | P28: ※Accommodation fee is actual cost including breakfast. | AA28: （２） | AB28: 宿泊費（実費） | AE28: 32 | AF28: 人･泊 | AG28: 6500 | AH28: =IF(COUNT(AE28:AG28)=0,"",AE28*AG28) -> 208000 | AK28: ※宿泊は、朝食を含む実費とする。
P29: ※Daily allowance is from departure day to arrival day. | AA29: （３） | AB29: 日当 | AC29: （別表による） | AE29: 32 | AF29: 人･日 | AG29: 4000 | AH29: =IF(COUNT(AE29:AG29)=0,"",AE29*AG29) -> 128000 | AK29: ※日当は、出発した日から、帰着した日までが対象。
N30: =IF(COUNT(G30)=0,"",G30*M30) | AA30: （４） | AB30: 機材運送費 | AE30: 一 | AF30: 式 | AH30: 120000
N31: =IF(COUNT(G31)=0,"",G31*M31) | AA31: （５） | AB31: 機器損料 | AE31: 一 | AF31: 式 | AH31: 0
N32: =IF(COUNT(G32)=0,"",G32*M32) | AA32: （６） | AB32: 消耗品 | AE32: 一 | AF32: 式 | AH32: 0
P33: ※Immunization should be charged an actual cost price including man-hour spent | AA33: （７） | AB33: その他経費 | AK33: ※予防注射等はすべて実費請求。要した工数（時間）も請求となる。
I34: =IF(COUNT(G34)=0,"",M34*$N$8) | AB34: ①ビザ取得費 | AE34: 一 | AF34: 式 | AH34: 20000
I35: =IF(COUNT(G35)=0,"",M35*$N$8) | J35: =IF(COUNT(G35:I35)=0,"",G35*I35) | N35: =IF(COUNT(G35)=0,"",G35*M35) | AB35: ②保険料 | AE35: 一 | AF35: 式 | AH35: 50000
AB36: ③その他 | AE36: 一 | AF36: 式 | AH36: 0
AA37: 小計 | AH37: =SUM(AH27:AH36) -> 764000
AH38: =IF(COUNT(AE38:AG38)=0,"",AE38*AG38)
I39: =IF(COUNT(G39)=0,"",M39*$N$8) | J39: =IF(COUNT(G39:I39)=0,"",G39*I39) | N39: =IF(COUNT(G39)=0,"",G39*M39) | Z39: ３．分析費 | AH39: =IF(COUNT(AE39:AG39)=0,"",AE39*AG39)
I40: =IF(COUNT(G40)=0,"",M40*$N$8) | J40: =IF(COUNT(G40:I40)=0,"",G40*I40) | N40: =IF(COUNT(G40)=0,"",G40*M40) | AA40: （１） | AB40: SOx | AE40: 20 | AF40: 検体 | AG40: 3000 | AH40: =IF(COUNT(AE40:AG40)=0,"",AE40*AG40) -> 60000
I41: =IF(COUNT(G41)=0,"",M41*$N$8) | J41: =IF(COUNT(G41:I41)=0,"",G41*I41) | N41: =IF(COUNT(G41)=0,"",G41*M41) | AA41: （２） | AB41: SO3 | AE41: 20 | AF41: 検体 | AG41: 3000 | AH41: =IF(COUNT(AE41:AG41)=0,"",AE41*AG41) -> 60000
I42: =IF(COUNT(G42)=0,"",M42*$N$8) | J42: =IF(COUNT(G42:I42)=0,"",G42*I42) | N42: =IF(COUNT(G42)=0,"",G42*M42) | AA42: （３） | AB42: NH3 | AE42: 20 | AF42: 検体 | AG42: 3000 | AH42: =IF(COUNT(AE42:AG42)=0,"",AE42*AG42) -> 60000
I43: =IF(COUNT(G43)=0,"",M43*$N$8) | J43: =IF(COUNT(G43:I43)=0,"",G43*I43) | N43: =IF(COUNT(G43)=0,"",G43*M43) | AA43: （４） | AB43: NOx | AE43: 20 | AF43: 検体 | AG43: 3000 | AH43: =IF(COUNT(AE43:AG43)=0,"",AE43*AG43) -> 60000
I44: =IF(COUNT(G44)=0,"",M44*$N$8) | J44: =IF(COUNT(G44:I44)=0,"",G44*I44) | N44: =IF(COUNT(G44)=0,"",G44*M44) | AA44: （５） | AB44: HCl | AE44: 20 | AF44: 検体 | AG44: 3000 | AH44: =IF(COUNT(AE44:AG44)=0,"",AE44*AG44) -> 60000
I45: =IF(COUNT(G45)=0,"",M45*$N$8) | J45: =IF(COUNT(G45:I45)=0,"",G45*I45) | N45: =IF(COUNT(G45)=0,"",G45*M45) | AA45: 小計 | AH45: =SUM(AH40:AH44) -> 300000
I46: =IF(COUNT(G46)=0,"",M46*$N$8) | J46: =IF(COUNT(G46:I46)=0,"",G46*I46) | N46: =IF(COUNT(G46)=0,"",G46*M46)
I47: =IF(COUNT(G47)=0,"",M47*$N$8) | J47: =IF(COUNT(G47:I47)=0,"",G47*I47) | N47: =IF(COUNT(G47)=0,"",G47*M47) | Z47: ４．会社経費 | AE47: 15 | AF47: ％ | AH47: =(AH24+AH37+AH45)*0.15 -> 354412.5
I48: =IF(COUNT(G48)=0,"",M48*$N$8) | J48: =IF(COUNT(G48:I48)=0,"",G48*I48) | N48: =IF(COUNT(G48)=0,"",G48*M48)
I49: =IF(COUNT(G49)=0,"",M49*$N$8) | J49: =IF(COUNT(G49:I49)=0,"",G49*I49) | N49: =IF(COUNT(G49)=0,"",G49*M49) | AH49: =IF(COUNT(AE49:AG49)=0,"",AE49*AG49)
C50: Tổng | J50: =J19+J26 -> 103600000 | N50: =N21+N29+N34+N38 -> 0 | AA50: 業務費 合計 | AH50: =ROUNDDOWN(AH24+AH37+AH45+AH47,-3) -> 2717000
C51: VAT | G51: 0 | H51: % | J51: =J50*G51/100 -> 0 | N51: =N50*R51/100 -> 0 | Q51: VAT= | R51: 10 | S51: % | AA51: VAT | AE51: 10 | AF51: ％ | AH51: =AH50*AE51% -> 271700
B52: Tổng giá | J52: =J50+J51 -> 103600000 | N52: =N50+N51 -> 0 | Q52: VAT need in Vietnam | Z52: 合 計 | AH52: =AH50+AH51 -> 2988700

Sheet 4.Handing Over
C2: CÔNG TY TNHH CHUGAI TECHNOS VIỆT NAM
E3: 66 Cao Triều Phát, Khu phố Hưng Gia 4, Phường Tân Phong, Quận 7, Tp.HCM , Việt Nam
E6: Điện thoại：08-5410-9111 ； Fax：08-5410-9222
F8: Website： | H8: http://www.chugai-tec-vn.com/jp
A9: BIÊN BẢN BÀN GIAO
A13: Ngày： | B13: 11/05/2017 | L13: Date： | N13: 42858
A15: Công ty: | B15: CÔNG TY TNHH VẬT LIỆU MỚI DENKA VIỆT NAM
A17: Địa chỉ: | B17: Lô D-5, Khu Công Nghiệp Thăng Long II, Xã Liêu Xá 3, Huyện Yên Mỹ, Tỉnh Hưng Yên, Việt Nam
A19: Điện thoại： | B19: +84-221-3974-805
A20: Fax： | B20: +84-221-3974-806
A22: Kính gửi quý công ty,
A23: Chúng tôi đã hoàn thành dịch vụ, theo đó chúng tôi muốn báo cáo như dưới đây.
A24: Vui lòng xác nhận dịch vụ đã được hoàn thành bằng chữ ký ở cuối biên bản bàn giao.
A25: Nếu quý công ty có thắc mắc, vui lòng liên hệ với chúng tôi.
A26: Sự hợp tác của quý công ty sẽ được đánh giá cao.
A28: Nội dung：
A29: Nội dung dịch vụ | D29: ='2.Quotation Service Order'!B25 -> Kiểm tra PT mối hàn của thùng chứa | L29: If some reports exist, write circulation here
D31: Báo cáo kiểm tra | L31: original： | M31: 2 | N31: Copy： | O31: 4
A33: Điều kiện：
A34: Ngày hoàn thành dịch vụ | D34: 11/05/2017 | L34: Service completion date
A35: Địa điểm | D35: ='1.Service Contraction'!E46 -> CÔNG TY TNHH VẬT LIỆU MỚI DENKA VIỆT NAM
A36: Quốc gia | D36: ='1.Service Contraction'!E47 -> Việt Nam
A37: Ghi chú | D37: Dựa vào | E37: Hợp đồng số | H37: ='1.Service Contraction'!E7 -> CCTVN - DAV-201704-01
E38: Báo giá/Số yêu cầu thanh toán | H38: ='2.Quotation Service Order'!B14 -> QCTVN201704-01
A40: Tổng giá trị hợp đồng: | C40: 103,600,000 VNĐ
A42: Tổng chi phí： | C42: 103,600,000 VNĐ
A44: Giá trên không bao gồm 10% VAT
A47: ='1.Service Contraction'!D17 -> CÔNG TY TNHH VẬT LIỆU MỚI DENKA VIỆT NAM | F47: =C2 -> CÔNG TY TNHH CHUGAI TECHNOS VIỆT NAM
A49: Ngày： | B49: =B13 -> 11/05/2017 | F49: Ngày： | G49: =B13 -> 11/05/2017
A55: Chữ ký và đóng dấu công ty | F55: Chữ ký và đóng dấu công ty

Sheet 5.Request for Payment
C2: CÔNG TY TNHH CHUGAI TECHNOS VIỆT NAM
E3: 66 Cao Triều Phát, Khu phố Hưng Gia 4, Phường Tân Phong, Quận 7, Tp.HCM , Việt Nam
E6: Điện thoại：08-5410-9111 ； Fax：08-5410-9222
F8: Website： | H8: http://www.chugai-tec-vn.com/jp
A9: YÊU CẦU THANH TOÁN
A13: Ngày： | B13: 11/05/2017 | L13: Date： | N13: 42858
A15: Công ty: | B15: CÔNG TY TNHH VẬT LIỆU MỚI DENKA VIỆT NAM
A17: Địa chỉ: | B17: Lô D-5, Khu Công Nghiệp Thăng Long II, Xã Liêu Xá 3, Huyện Yên Mỹ, Tỉnh Hưng Yên, Việt Nam
A19: Điện thoại： | B19: +84-221-3974-805
A20: Fax： | B20: +84-221-3974-806
A22: Kính gửi quý công ty,
A23: Căn cứ theo hợp đồng số: CCTVN - DAV-201704-1 được làm vào ngày 18/04/2017 giữa công ty TNHH Vật Liệu Mới DENKA Việt Nam và công ty TNHH Chugai Technos Việt Nam, vui lòng chuyển khoản cho chúng tôi tổng số tiền dưới đây: | K23: Căn cứ theo hợp đồng số: CCTVN - DAV-201704-1 được làm vào ngày 18/04/2017 giữa công ty TNHH Vật Liệu Mới DENKA Việt Nam và công ty TNHH Chugai Technos Việt Nam, vui lòng chuyển khoản cho chúng tôi tổng số tiền dưới đây:
A27: 103,600,000 VNĐ
A29: Tổng số tiền | C29: 103600000 | E29: VNĐ
A33: Tổng tiền cần thanh toán： | C33: =C29+C30 -> 103600000 | E33: VNĐ
M36: only | N36: Twenty Four | P36: thousand
A37: Vui lòng chuyển khoản đến tài khoản CÔNG TY TNHH CHUGAI TECHNOS VIỆT NAM như sau: | N37: Thirty
A39: Chủ tài khoản | C39: ： | D39: ='1.Service Contraction'!D35 -> CÔNG TY TNHH CHUGAI TECHNOS VIỆT NAM
A40: Số tài khoản | C40: ： | D40: ='1.Service Contraction'!D36 -> 10065702 | F40: VNĐ
A41: Ngân hàng | C41: ： | D41: ='1.Service Contraction'!D37 -> Sumitomo Mitsui Banking Corporation － Ho Chi Minh Branch
F44: Cảm ơn sự hợp tác của quý công ty
F45: Trân trọng
F47: =D39 -> CÔNG TY TNHH CHUGAI TECHNOS VIỆT NAM
F55: ='1.Service Contraction'!D28 -> Ông MASAMI OUE

Sheet 6.Invoice
B3: CÔNG TY TNHH CHUGAI TECHNOS VIỆT NAM | I3: HÓA ĐƠN
H4: Ngày phát hành: | I4: 03/05/2017
B5: Địa chỉ : 66 Cao Triều Phát, Khu phố Hưng Gia 4, Phường Tân Phong, Quận 7, Tp.HCM, Việt Nam
B8: Điện thoại / Fax : +84-8-54109111/ +84-8-54109222
B11: KÍNH GỬI:
B12: CÔNG TY TNHH VẬT LIỆU MỚI DENKA VIỆT NAM | F12: SỐ HÓA ĐƠN: | H12: ='1.Service Contraction'!E7 -> CCTVN - DAV-201704-01
B13: Địa chỉ: Lô D-5, Khu Công Nghiệp Thăng Long II, Xã Liêu Xá 3, Huyện Yên Mỹ, Tỉnh Hưng Yên, Việt Nam | F13: NGÀY PHÁT HÀNH: | H13: ='4.Handing Over'!N13 -> 42858
F14: SỐ HỢP ĐỒNG: | H14: =H12 -> CCTVN - DAV-201704-01
F15: NGÀY PHÁT HÀNH: | H15: ='1.Service Contraction'!P15 -> 18-Apr-17
B21: NỘI DUNG DỊCH VỤ | H21: ĐƠN GIÁ | I21: SỐ LƯỢNG
H22: VND | I22: UNIT
B23: Dịch vụ： | C23: Kiểm tra PT mối hàn của thùng chứa
C24: ='2.Quotation Service Order'!C26 -> Chi phí nhân công | H24: ='2.Quotation Service Order'!G26 -> 86000000 | I24: 1
C25: ='2.Quotation Service Order'!C27 -> Chi phí | H25: ='2.Quotation Service Order'!G27 -> 17600000 | I25: 1
I28: =IF(H28,H28*B28,"")
F29: Tổng tiền | H29: VND | I29: ='2.Quotation Service Order'!G28 -> 103600000
F30: VAT | H30: VND | I30: 0
F31: Tổng | H31: VND | I31: =I29+I30 -> 103600000
F32: ='1.Service Contraction'!B58 -> 0
F35: CÔNG TY TNHH CHUGAI TECHNOS VIỆT NAM
F40: Tổng giám đốc: MASAMI OUE

Sheet 7. Process Sheet
B2: To | C2: ='1.Service Contraction'!D17 -> CÔNG TY TNHH VẬT LIỆU MỚI DENKA VIỆT NAM | N2: ='1.Service Contraction'!D35 -> CÔNG TY TNHH CHUGAI TECHNOS VIỆT NAM
B3: Site name： | C3: ='1.Service Contraction'!E47 -> Việt Nam | E3: ='1.Service Contraction'!E46 -> CÔNG TY TNHH VẬT LIỆU MỚI DENKA VIỆT NAM
Q4: Creation Date： | R4: 42616
B6: Date | C6: Day | D6: Business content | E6: Working Time | I6: Head-count | J6: Travel Cost | O6: Daily payment | Q6: Breakdown of man-hour
E7: Start | F7: Finish | G7: Rest | H7: Hours | J7: Departure Place | K7: Arrival Place | L7: Transportation | M7: Transportation Fee(USD) | N7: Numbers of Nights | O7: Engineer | P7: Overtime | Q7: Engineers
O8: 18 | Q8: Man-hour | R8: Trip | S8: Man-hour | T8: Overtime
B9: 42776 | C9: =IF(COUNT(B9)=0,"",TEXT(B9,"ddd")) -> Fri | D9: Custom procedure | E9: 0.33333333 | F9: 0.70833333 | G9: 0.041666667 | H9: =IF(COUNT(E9:F9)=0,"",(DAY(F9-E9-G9))*24+HOUR(F9-E9-G9)+(MINUTE(F9-E9-G9)/60)) -> 8 | I9: 1 | J9: Chugai Technos | K9: Chugai Technos | L9: Taxi
B10: 42777 | C10: =IF(COUNT(B10)=0,"",TEXT(B10,"ddd")) -> Sat | D10: Preparation | E10: 0.33333333 | F10: 0.70833333 | G10: 0.041666667 | H10: =IF(COUNT(E10:F10)=0,"",(DAY(F10-E10-G10))*24+HOUR(F10-E10-G10)+(MINUTE(F10-E10-G10)/60)) -> 8 | I10: 1
B11: 42778 | C11: =IF(COUNT(B11)=0,"",TEXT(B11,"ddd")) -> Sun | H11: =IF(COUNT(E11:F11)=0,"",(DAY(F11-E11-G11))*24+HOUR(F11-E11-G11)+(MINUTE(F11-E11-G11)/60))
B12: 42779 | C12: =IF(COUNT(B12)=0,"",TEXT(B12,"ddd")) -> Mon | D12: Transportation | E12: 0.25 | F12: 0.625 | G12: 0.041666667 | H12: =IF(COUNT(E12:F12)=0,"",(DAY(F12-E12-G12))*24+HOUR(F12-E12-G12)+(MINUTE(F12-E12-G12)/60)) -> 8 | I12: 1 | J12: Chugai Technos | K12: Yazaki | L12: Taxi,Air | P12: 2
C13: =IF(COUNT(B13)=0,"",TEXT(B13,"ddd")) | D13: Meeting | E13: 0.625 | F13: 0.70833333 | H13: =IF(COUNT(E13:F13)=0,"",(DAY(F13-E13-G13))*24+HOUR(F13-E13-G13)+(MINUTE(F13-E13-G13)/60)) -> 2 | I13: 1 | J13: Yazaki | K13: Yazaki | O13: 1
C14: =IF(COUNT(B14)=0,"",TEXT(B14,"ddd")) | D14: Transportation | E14: 0.70833333 | F14: 0.77083333 | I14: 1 | J14: Yazaki | K14: Yazaki
B15: 42780 | C15: =IF(COUNT(B15)=0,"",TEXT(B15,"ddd")) -> Tue | D15: Transportation | E15: 0.27083333 | F15: 0.33333333 | I15: 1 | J15: Yazaki | K15: Chugai Technos | L15: Taxi,Air
C16: =IF(COUNT(B16)=0,"",TEXT(B16,"ddd")) | D16: Measurement | E16: 0.33333333 | F16: 0.66666667 | G16: 0.041666667 | H16: =IF(COUNT(E16:F16)=0,"",(DAY(F16-E16-G16))*24+HOUR(F16-E16-G16)+(MINUTE(F16-E16-G16)/60)) -> 7 | I16: 1 | O16: 1
C17: =IF(COUNT(B17)=0,"",TEXT(B17,"ddd")) | D17: Transportation | E17: 0.66666667 | F17: 1 | H17: =IF(COUNT(E17:F17)=0,"",(DAY(F17-E17-G17))*24+HOUR(F17-E17-G17)+(MINUTE(F17-E17-G17)/60)) -> 8 | I17: 1
B18: 42781 | C18: =IF(COUNT(B18)=0,"",TEXT(B18,"ddd")) -> Wed | D18: Clearance | E18: 0.33333333 | F18: 0.70833333 | G18: 0.041666667 | H18: =IF(COUNT(E18:F18)=0,"",(DAY(F18-E18-G18))*24+HOUR(F18-E18-G18)+(MINUTE(F18-E18-G18)/60)) -> 8 | I18: 1
C19: =IF(COUNT(B19)=0,"",TEXT(B19,"ddd")) | D19: Report | E19: 0.33333333 | F19: 0.70833333 | G19: 0.041666667 | H19: =IF(COUNT(E19:F19)=0,"",(DAY(F19-E19-G19))*24+HOUR(F19-E19-G19)+(MINUTE(F19-E19-G19)/60)) -> 8 | I19: 1
C20: =IF(COUNT(B20)=0,"",TEXT(B20,"ddd")) | D20: Shipping procedure | E20: 0.33333333 | F20: 0.625 | G20: 0.041666667 | H20: =IF(COUNT(E20:F20)=0,"",(DAY(F20-E20-G20))*24+HOUR(F20-E20-G20)+(MINUTE(F20-E20-G20)/60)) -> 6 | I20: 1
C21: =IF(COUNT(B21)=0,"",TEXT(B21,"ddd")) | H21: =IF(COUNT(E21:F21)=0,"",(DAY(F21-E21-G21))*24+HOUR(F21-E21-G21)+(MINUTE(F21-E21-G21)/60))
C22: =IF(COUNT(B22)=0,"",TEXT(B22,"ddd")) | H22: =IF(COUNT(E22:F22)=0,"",(DAY(F22-E22-G22))*24+HOUR(F22-E22-G22)+(MINUTE(F22-E22-G22)/60))
C23: =IF(COUNT(B23)=0,"",TEXT(B23,"ddd")) | H23: =IF(COUNT(E23:F23)=0,"",(DAY(F23-E23-G23))*24+HOUR(F23-E23-G23)+(MINUTE(F23-E23-G23)/60))
C24: =IF(COUNT(B24)=0,"",TEXT(B24,"ddd")) | H24: =IF(COUNT(E24:F24)=0,"",(DAY(F24-E24-G24))*24+HOUR(F24-E24-G24)+(MINUTE(F24-E24-G24)/60))
C25: =IF(COUNT(B25)=0,"",TEXT(B25,"ddd")) | H25: =IF(COUNT(E25:F25)=0,"",(DAY(F25-E25-G25))*24+HOUR(F25-E25-G25)+(MINUTE(F25-E25-G25)/60))
C26: =IF(COUNT(B26)=0,"",TEXT(B26,"ddd")) | H26: =IF(COUNT(E26:F26)=0,"",(DAY(F26-E26-G26))*24+HOUR(F26-E26-G26)+(MINUTE(F26-E26-G26)/60))
C27: =IF(COUNT(B27)=0,"",TEXT(B27,"ddd"))
C28: =IF(COUNT(B28)=0,"",TEXT(B28,"ddd"))
C29: =IF(COUNT(B29)=0,"",TEXT(B29,"ddd")) | H29: =IF(COUNT(E29:F29)=0,"",(DAY(F29-E29-G29))*24+HOUR(F29-E29-G29)+(MINUTE(F29-E29-G29)/60))
C30: =IF(COUNT(B30)=0,"",TEXT(B30,"ddd")) | H30: =IF(COUNT(E30:F30)=0,"",(DAY(F30-E30-G30))*24+HOUR(F30-E30-G30)+(MINUTE(F30-E30-G30)/60))
C31: =IF(COUNT(B31)=0,"",TEXT(B31,"ddd")) | H31: =IF(COUNT(E31:F31)=0,"",(DAY(F31-E31-G31))*24+HOUR(F31-E31-G31)+(MINUTE(F31-E31-G31)/60))
C32: =IF(COUNT(B32)=0,"",TEXT(B32,"ddd")) | H32: =IF(COUNT(E32:F32)=0,"",(DAY(F32-E32-G32))*24+HOUR(F32-E32-G32)+(MINUTE(F32-E32-G32)/60))
C33: =IF(COUNT(B33)=0,"",TEXT(B33,"ddd")) | H33: =IF(COUNT(E33:F33)=0,"",(DAY(F33-E33-G33))*24+HOUR(F33-E33-G33)+(MINUTE(F33-E33-G33)/60))
C34: =IF(COUNT(B34)=0,"",TEXT(B34,"ddd")) | H34: =IF(COUNT(E34:F34)=0,"",(DAY(F34-E34-G34))*24+HOUR(F34-E34-G34)+(MINUTE(F34-E34-G34)/60))
C35: =IF(COUNT(B35)=0,"",TEXT(B35,"ddd")) | H35: =IF(COUNT(E35:F35)=0,"",(DAY(F35-E35-G35))*24+HOUR(F35-E35-G35)+(MINUTE(F35-E35-G35)/60))
C36: =IF(COUNT(B36)=0,"",TEXT(B36,"ddd")) | H36: =IF(COUNT(E36:F36)=0,"",(DAY(F36-E36-G36))*24+HOUR(F36-E36-G36)+(MINUTE(F36-E36-G36)/60))
C37: =IF(COUNT(B37)=0,"",TEXT(B37,"ddd")) | H37: =IF(COUNT(E37:F37)=0,"",(DAY(F37-E37-G37))*24+HOUR(F37-E37-G37)+(MINUTE(F37-E37-G37)/60))
C38: =IF(COUNT(B38)=0,"",TEXT(B38,"ddd")) | H38: =IF(COUNT(E38:F38)=0,"",(DAY(F38-E38-G38))*24+HOUR(F38-E38-G38)+(MINUTE(F38-E38-G38)/60))
C39: =IF(COUNT(B39)=0,"",TEXT(B39,"ddd")) | H39: =IF(COUNT(E39:F39)=0,"",(DAY(F39-E39-G39))*24+HOUR(F39-E39-G39)+(MINUTE(F39-E39-G39)/60))
B40: Total | H40: =SUM(H9:H39) -> 63 | I40: =SUM(I9:I39) -> 11 | M40: =SUM(M9:M39) -> 0 | N40: =SUM(N9:N39) -> 0 | O40: =SUM(O9:O39) -> 2 | P40: =SUM(P9:P39) -> 2 | Q40: =SUM(Q9:Q39) -> 0 | R40: =SUM(R9:R39) -> 0 | S40: =SUM(S9:S39) -> 0 | T40: =SUM(T9:T39) -> 0
M41: =IF(COUNT(J41:L41)=0,"",J41*L41)

Sheet 8.Allowance and Others
A1: A．Day pay and accommodation fee | G1: B．Overtime Money
E2: Currency：USD | M2: Currency：JPY
B3: Group 1 | C3: Group 2 | D3: Group 3 | E3: In Vietnam | G3: Total salary | H3: Basic unit price(A) | I3: Weekday | K3: Holiday(Sat and Sun） | M3: Public holiday
A4: Daily pay | B4: 25 | C4: 18 | D4: 9 | E4: 9 | I4: Day | J4: Midnight | K4: Day | L4: Midnight | M4: Day | N4: Midnight
A5: Accommodation | B5: Actual costs and expenses | G5: 35000 | H5: =G5/22/8 -> 198.86364 | I5: =H5*1.5 -> 298.29545 | J5: =H5*1.5+H5*0.3+H5*0.2 -> 397.72727 | K5: =H5*2 -> 397.72727 | L5: =H5*2+H5*0.3+H5*2*0.2 -> 536.93182 | M5: =H5*3 -> 596.59091 | N5: =H5*3+H5*0.3+H5*3*0.2 -> 775.56818
A6: Country | B6: IRELAND UK AND NORTHERN IRELAND AUSTRIA BELGIUM PORTUGAL CANADA GERMANY TAIWAN DENMARK NEITHERLAND SOUTH KOREA ITALIA LUXEMBOURG USA NORWAY JAPAN FINLAND FRANCE SPAIN SWEDEN SWITZERLAND RUSSIA TURKEY UKRAINA | C6: AGENTINA EGYPT SAUDI ARABIA POLAND BAREN BELARUS BOLIVIA BOSNIA AND HECXEGOVINA BRAXIN BRUNEI BUNGARI UNIFIED ARAB EMIRATES (UAE) REPUBLIC OF CZECH REPUBLIC OF SLOVAKIA CHILE KUWAIT COLOMBIA CROATIA ESTONIA JORDAN HONG KONG HUNGARI ISRAEL LATVIA LEBANON INDIA LITHUANA MACAU MACEDONIA MALTA MEXICO MOLDOVIA SOUTH AFRICA SECBIA MONGTENEGRO NEW ZEALAND AUSTRALIA PANAMA PERU QUATA RUMANI SAMOA SINGGAPORE SLOVENIA CHINA URUGUAY | D6: DOMINICA ARMENIA ANGIERI ANGOLA APGHANISTAN AZECBAIZAN BANGLADESH CAMBODIA DEMOCRATIC PEOPLE'S REPUBLIC OF KOREA REPUBLIC OF GUINEA REPUBLIC OF YEMEN CONGO COSTARICA CUBA EAST SAHARA EAST TIMO ECUADOR ETHIOPIA ELSALVADO ERITRE FIJI GHANA GRENADA GRUZIA GUATEMALA HAITI HONDURAS IRAN INDONESIA JAMAICA KAZACSTAN KENIA KYRGYZSTAN LAOS LIBI MADAGASCAR MALAYSIA MALI MARITUS MAROC MONGOLIA MYANMAR NEPAL NICARAGOA PAKISTAN PHILIPIN SHIP SRILANCA TAJIKISTAN TANZANIA THAILAND TURKMENISTAN UZBEKISTAN VENEZUELA SOMALI XYRIA Other countries not belonging to the above groups | E6: Evenness | G6: 45000 | H6: =G6/22/8 -> 255.68182 | I6: =H6*1.5 -> 383.52273 | J6: =H6*1.5+H6*0.3+H6*0.2 -> 511.36364 | K6: =H6*2 -> 511.36364 | L6: =H6*2+H6*0.3+H6*2*0.2 -> 690.34091 | M6: =H6*3 -> 767.04545 | N6: =H6*3+H6*0.3+H6*3*0.2 -> 997.15909
G7: 70000 | H7: =G7/22/8 -> 397.72727 | I7: =H7*1.5 -> 596.59091 | J7: =H7*1.5+H7*0.3+H7*0.2 -> 795.45455 | K7: =H7*2 -> 795.45455 | L7: =H7*2+H7*0.3+H7*2*0.2 -> 1073.8636 | M7: =H7*3 -> 1193.1818 | N7: =H7*3+H7*0.3+H7*3*0.2 -> 1551.1364
G8: 100000 | H8: =G8/22/8 -> 568.18182 | I8: =H8*1.5 -> 852.27273 | J8: =H8*1.5+H8*0.3+H8*0.2 -> 1136.3636 | K8: =H8*2 -> 1136.3636 | L8: =H8*2+H8*0.3+H8*2*0.2 -> 1534.0909 | M8: =H8*3 -> 1704.5455 | N8: =H8*3+H8*0.3+H8*3*0.2 -> 2215.9091
G9: 120000 | H9: =G9/22/8 -> 681.81818 | I9: =H9*1.5 -> 1022.7273 | J9: =H9*1.5+H9*0.3+H9*0.2 -> 1363.6364 | K9: =H9*2 -> 1363.6364 | L9: =H9*2+H9*0.3+H9*2*0.2 -> 1840.9091 | M9: =H9*3 -> 2045.4545 | N9: =H9*3+H9*0.3+H9*3*0.2 -> 2659.0909
G10: ※Ａ＝Basic Salary／22days／8 hours
G11: Midnight Overtime is between p.m 21:00 and a.m 5:00
A53: In accordance with the Vietnamese government notices of Article 2, paragraph （5） of 97/2012/TT-BTC and Article 6, paragraph （2.8） of 123/2012/TT-BTC

Sheet 9.Instrument Breakdown Sheet
D2: Breakdown Sheet of Instrument Depreciation
G3: =#REF! -> #REF!
B4: No. | I4: =#REF! -> #REF!
D5: Instrument name | E5: Instrument depreciation unit price | F5: Consumables unit price | G5: Taking out quantities | H5: Taking out days | I5: Instrument depreciation | J5: Used days | K5: Consumables cost
D6: =IF(B6="","",VLOOKUP(B6,'10.Equipment depreciation table'!$B$3:$E$52,2)) | E6: =IF(B6="","",VLOOKUP(B6,'10.Equipment depreciation table'!$B$3:$E$52,3)) | F6: =IF(B6="","",VLOOKUP(B6,'10.Equipment depreciation table'!$B$3:$E$52,4)) | I6: =IF(H6=0,"",E6*G6*H6) | K6: =IF(G6=0,"",F6*G6*J6)
D7: =IF(B7="","",VLOOKUP(B7,'10.Equipment depreciation table'!$B$3:$E$52,2)) | E7: =IF(B7="","",VLOOKUP(B7,'10.Equipment depreciation table'!$B$3:$E$52,3)) | F7: =IF(B7="","",VLOOKUP(B7,'10.Equipment depreciation table'!$B$3:$E$52,4)) | I7: =IF(H7=0,"",E7*G7*H7) | K7: =IF(G7=0,"",F7*G7*J7)
D8: =IF(B8="","",VLOOKUP(B8,'10.Equipment depreciation table'!$B$3:$E$52,2)) | E8: =IF(B8="","",VLOOKUP(B8,'10.Equipment depreciation table'!$B$3:$E$52,3)) | F8: =IF(B8="","",VLOOKUP(B8,'10.Equipment depreciation table'!$B$3:$E$52,4)) | I8: =IF(H8=0,"",E8*G8*H8) | K8: =IF(G8=0,"",F8*G8*J8)
D9: =IF(B9="","",VLOOKUP(B9,'10.Equipment depreciation table'!$B$3:$E$52,2)) | E9: =IF(B9="","",VLOOKUP(B9,'10.Equipment depreciation table'!$B$3:$E$52,3)) | F9: =IF(B9="","",VLOOKUP(B9,'10.Equipment depreciation table'!$B$3:$E$52,4)) | I9: =IF(H9=0,"",E9*G9*H9) | K9: =IF(G9=0,"",F9*G9*J9)
D10: =IF(B10="","",VLOOKUP(B10,'10.Equipment depreciation table'!$B$3:$E$52,2)) | E10: =IF(B10="","",VLOOKUP(B10,'10.Equipment depreciation table'!$B$3:$E$52,3)) | F10: =IF(B10="","",VLOOKUP(B10,'10.Equipment depreciation table'!$B$3:$E$52,4)) | I10: =IF(H10=0,"",E10*G10*H10) | K10: =IF(G10=0,"",F10*G10*J10)
D11: =IF(B11="","",VLOOKUP(B11,'10.Equipment depreciation table'!$B$3:$E$52,2)) | E11: =IF(B11="","",VLOOKUP(B11,'10.Equipment depreciation table'!$B$3:$E$52,3)) | F11: =IF(B11="","",VLOOKUP(B11,'10.Equipment depreciation table'!$B$3:$E$52,4)) | I11: =IF(H11=0,"",E11*G11*H11) | K11: =IF(G11=0,"",F11*G11*J11)
D12: =IF(B12="","",VLOOKUP(B12,'10.Equipment depreciation table'!$B$3:$E$52,2)) | E12: =IF(B12="","",VLOOKUP(B12,'10.Equipment depreciation table'!$B$3:$E$52,3)) | F12: =IF(B12="","",VLOOKUP(B12,'10.Equipment depreciation table'!$B$3:$E$52,4)) | I12: =IF(H12=0,"",E12*G12*H12) | K12: =IF(G12=0,"",F12*G12*J12)
D13: =IF(B13="","",VLOOKUP(B13,'10.Equipment depreciation table'!$B$3:$E$52,2)) | E13: =IF(B13="","",VLOOKUP(B13,'10.Equipment depreciation table'!$B$3:$E$52,3)) | F13: =IF(B13="","",VLOOKUP(B13,'10.Equipment depreciation table'!$B$3:$E$52,4)) | I13: =IF(H13=0,"",E13*G13*H13) | K13: =IF(G13=0,"",F13*G13*J13)
D14: =IF(B14="","",VLOOKUP(B14,'10.Equipment depreciation table'!$B$3:$E$52,2)) | E14: =IF(B14="","",VLOOKUP(B14,'10.Equipment depreciation table'!$B$3:$E$52,3)) | F14: =IF(B14="","",VLOOKUP(B14,'10.Equipment depreciation table'!$B$3:$E$52,4)) | I14: =IF(H14=0,"",E14*G14*H14) | K14: =IF(G14=0,"",F14*G14*J14)
D15: =IF(B15="","",VLOOKUP(B15,'10.Equipment depreciation table'!$B$3:$E$52,2)) | E15: =IF(B15="","",VLOOKUP(B15,'10.Equipment depreciation table'!$B$3:$E$52,3)) | F15: =IF(B15="","",VLOOKUP(B15,'10.Equipment depreciation table'!$B$3:$E$52,4)) | I15: =IF(H15=0,"",E15*G15*H15) | K15: =IF(G15=0,"",F15*G15*J15)
D16: =IF(B16="","",VLOOKUP(B16,'10.Equipment depreciation table'!$B$3:$E$52,2)) | E16: =IF(B16="","",VLOOKUP(B16,'10.Equipment depreciation table'!$B$3:$E$52,3)) | F16: =IF(B16="","",VLOOKUP(B16,'10.Equipment depreciation table'!$B$3:$E$52,4)) | I16: =IF(H16=0,"",E16*G16*H16) | K16: =IF(G16=0,"",F16*G16*J16)
D17: =IF(B17="","",VLOOKUP(B17,'10.Equipment depreciation table'!$B$3:$E$52,2)) | E17: =IF(B17="","",VLOOKUP(B17,'10.Equipment depreciation table'!$B$3:$E$52,3)) | F17: =IF(B17="","",VLOOKUP(B17,'10.Equipment depreciation table'!$B$3:$E$52,4)) | I17: =IF(H17=0,"",E17*G17*H17) | K17: =IF(G17=0,"",F17*G17*J17)
... D47: =IF(B47="","",VLOOKUP(B47,'10.Equipment depreciation table'!$B$3:$E$52,2)) | E47: =IF(B47="","",VLOOKUP(B47,'10.Equipment depreciation table'!$B$3:$E$52,3)) | F47: =IF(B47="","",VLOOKUP(B47,'10.Equipment depreciation table'!$B$3:$E$52,4)) | I47: =IF(H47=0,"",E47*G47*H47) | K47: =IF(G47=0,"",F47*G47*J47)
D48: =IF(B48="","",VLOOKUP(B48,'10.Equipment depreciation table'!$B$3:$E$52,2)) | E48: =IF(B48="","",VLOOKUP(B48,'10.Equipment depreciation table'!$B$3:$E$52,3)) | F48: =IF(B48="","",VLOOKUP(B48,'10.Equipment depreciation table'!$B$3:$E$52,4)) | H48: Total | I48: =SUM(I6:I47) -> 0 | J48: Total | K48: =SUM(K6:K47) -> 0
D49: =IF(B49="","",VLOOKUP(B49,'10.Equipment depreciation table'!$B$3:$E$52,2)) | E49: =IF(B49="","",VLOOKUP(B49,'10.Equipment depreciation table'!$B$3:$E$52,3)) | F49: =IF(B49="","",VLOOKUP(B49,'10.Equipment depreciation table'!$B$3:$E$52,4)) | G49: Equipment depreciation Total | J49: =I48+K48 -> 0

Sheet 10.Equipment depreciation table
B2: No. | C2: Equipment Name | D2: Equipment depreciation | E2: Consumables
B3: 1 | C3: NOx-O2 monitor | D3: 113.1 | E3: 34.8
B4: 2 | C4: CO2-CO-O2 monitor | D4: 139 | E4: 34.8
B5: 3 | C5: NOx-O2-SO2 monitor | D5: 139.1 | E5: 34.8
B6: 4 | C6: Orsat | D6: 13.1 | E6: 8.7
B7: 5 | C7: CO ( Drager detection tube ) | D7: 8.7 | E7: 7
B8: 6 | C8: CO ( Detection tube ) | D8: 8.7 | E8: 4.3
B9: 7 | C9: Moisture content measurement | D9: 13.1 | E9: 8.7
B10: 8 | C10: Velocity measurement | D10: 13.1 | E10: 13.1
B11: 9 | C11: Temperature measurement | D11: 13.1 | E11: 0
B12: 10 | C12: Dust (1set) | D12: 26.1 | E12: 30.5
B13: 11 | C13: SOx measurement | D13: 26.1 | E13: 30.5
B14: 12 | C14: SO3 measurement | D14: 26.1 | E14: 30.5
... B30: 28 | C30: Flow meter | D30: 10 | E30: 0
B31: 29 | C31: Standard gas | D31: cylinder・week | E31: 174
B32: 30 | C32: Teflon tube ( 4×6 ) | D32: m | E32: 10.5
B33: 31 | C33: Teflon tube ( 6×8 ) | D33: m | E33: 13.1
B34: 32 | C34: Teflon tube ( 8×10 ) | D34: m | E34: 17.4
B35: 33 | C35: Thimble filter ( Silica ) | D35: piece | E35: 8.7
B36: 34 | C36: Thimble filter ( 89S ) | D36: piece | E36: 26.1
B37: 35 | C37: Thimble filter ( 89 ) | D37: piece | E37: 30.5
B38: 36 | C38: Circular filter ( Teflon ) | D38: piece | E38: 4
B39: 37 | C39: Circular filter ( QM－A ) | D39: piece | E39: 3.5
B40: 38 | C40: Filter paper for Andersen | D40: piece | E40: 8.7
B41: 39 | C41: Silicon hose | D41: m | E41: 7
B42: 40 | C42: Vinyl hose | D42: m | E42: 1.6
... B48: 46 | C48: Plastic bottle | D48: piece | E48: 1
B49: 47
B50: 48
B51: 49
B52: 50

Sheet 11.Consumbles Breakudown Sheet
D2: Breakdown Sheet of consumables
G3: =#REF! -> #REF!
B4: No. | H4: =#REF! -> #REF!
D5: The name of ｃonsumables | E5: Unit | F5: Consumables unit price | G5: Quantities | H5: Consumables cost | I5: Remarks
D6: =IF(B6="","",VLOOKUP(B6,'10.Equipment depreciation table'!$B$3:$E$52,2)) | E6: =IF(B6="","",VLOOKUP(B6,'10.Equipment depreciation table'!$B$3:$E$52,3)) | F6: =IF(B6="","",VLOOKUP(B6,'10.Equipment depreciation table'!$B$3:$E$52,4)) | H6: =IF(G6=0,"",F6*G6)
D7: =IF(B7="","",VLOOKUP(B7,'10.Equipment depreciation table'!$B$3:$E$52,2)) | E7: =IF(B7="","",VLOOKUP(B7,'10.Equipment depreciation table'!$B$3:$E$52,3)) | F7: =IF(B7="","",VLOOKUP(B7,'10.Equipment depreciation table'!$B$3:$E$52,4)) | H7: =IF(G7=0,"",F7*G7)
D8: =IF(B8="","",VLOOKUP(B8,'10.Equipment depreciation table'!$B$3:$E$52,2)) | E8: =IF(B8="","",VLOOKUP(B8,'10.Equipment depreciation table'!$B$3:$E$52,3)) | F8: =IF(B8="","",VLOOKUP(B8,'10.Equipment depreciation table'!$B$3:$E$52,4)) | H8: =IF(G8=0,"",F8*G8)
D9: =IF(B9="","",VLOOKUP(B9,'10.Equipment depreciation table'!$B$3:$E$52,2)) | E9: =IF(B9="","",VLOOKUP(B9,'10.Equipment depreciation table'!$B$3:$E$52,3)) | F9: =IF(B9="","",VLOOKUP(B9,'10.Equipment depreciation table'!$B$3:$E$52,4)) | H9: =IF(G9=0,"",F9*G9)
D10: =IF(B10="","",VLOOKUP(B10,'10.Equipment depreciation table'!$B$3:$E$52,2)) | E10: =IF(B10="","",VLOOKUP(B10,'10.Equipment depreciation table'!$B$3:$E$52,3)) | F10: =IF(B10="","",VLOOKUP(B10,'10.Equipment depreciation table'!$B$3:$E$52,4)) | H10: =IF(G10=0,"",F10*G10)
D11: =IF(B11="","",VLOOKUP(B11,'10.Equipment depreciation table'!$B$3:$E$52,2)) | E11: =IF(B11="","",VLOOKUP(B11,'10.Equipment depreciation table'!$B$3:$E$52,3)) | F11: =IF(B11="","",VLOOKUP(B11,'10.Equipment depreciation table'!$B$3:$E$52,4)) | H11: =IF(G11=0,"",F11*G11)
D12: =IF(B12="","",VLOOKUP(B12,'10.Equipment depreciation table'!$B$3:$E$52,2)) | E12: =IF(B12="","",VLOOKUP(B12,'10.Equipment depreciation table'!$B$3:$E$52,3)) | F12: =IF(B12="","",VLOOKUP(B12,'10.Equipment depreciation table'!$B$3:$E$52,4)) | H12: =IF(G12=0,"",F12*G12)
D13: =IF(B13="","",VLOOKUP(B13,'10.Equipment depreciation table'!$B$3:$E$52,2)) | E13: =IF(B13="","",VLOOKUP(B13,'10.Equipment depreciation table'!$B$3:$E$52,3)) | F13: =IF(B13="","",VLOOKUP(B13,'10.Equipment depreciation table'!$B$3:$E$52,4)) | H13: =IF(G13=0,"",F13*G13)
D14: =IF(B14="","",VLOOKUP(B14,'10.Equipment depreciation table'!$B$3:$E$52,2)) | E14: =IF(B14="","",VLOOKUP(B14,'10.Equipment depreciation table'!$B$3:$E$52,3)) | F14: =IF(B14="","",VLOOKUP(B14,'10.Equipment depreciation table'!$B$3:$E$52,4)) | H14: =IF(G14=0,"",F14*G14)
D15: =IF(B15="","",VLOOKUP(B15,'10.Equipment depreciation table'!$B$3:$E$52,2)) | E15: =IF(B15="","",VLOOKUP(B15,'10.Equipment depreciation table'!$B$3:$E$52,3)) | F15: =IF(B15="","",VLOOKUP(B15,'10.Equipment depreciation table'!$B$3:$E$52,4)) | H15: =IF(G15=0,"",F15*G15)
D16: =IF(B16="","",VLOOKUP(B16,'10.Equipment depreciation table'!$B$3:$E$52,2)) | E16: =IF(B16="","",VLOOKUP(B16,'10.Equipment depreciation table'!$B$3:$E$52,3)) | F16: =IF(B16="","",VLOOKUP(B16,'10.Equipment depreciation table'!$B$3:$E$52,4)) | H16: =IF(G16=0,"",F16*G16)
D17: =IF(B17="","",VLOOKUP(B17,'10.Equipment depreciation table'!$B$3:$E$52,2)) | E17: =IF(B17="","",VLOOKUP(B17,'10.Equipment depreciation table'!$B$3:$E$52,3)) | F17: =IF(B17="","",VLOOKUP(B17,'10.Equipment depreciation table'!$B$3:$E$52,4)) | H17: =IF(G17=0,"",F17*G17)
... D47: =IF(B47="","",VLOOKUP(B47,'10.Equipment depreciation table'!$B$3:$E$52,2)) | E47: =IF(B47="","",VLOOKUP(B47,'10.Equipment depreciation table'!$B$3:$E$52,3)) | F47: =IF(B47="","",VLOOKUP(B47,'10.Equipment depreciation table'!$B$3:$E$52,4)) | H47: =IF(G47=0,"",F47*G47)
D48: =IF(B48="","",VLOOKUP(B48,'10.Equipment depreciation table'!$B$3:$E$52,2)) | E48: =IF(B48="","",VLOOKUP(B48,'10.Equipment depreciation table'!$B$3:$E$52,3)) | F48: =IF(B48="","",VLOOKUP(B48,'10.Equipment depreciation table'!$B$3:$E$52,4)) | G48: Total | H48: =SUM(H6:H47) -> 0

Sheet Balance sheet
B2: JPY／USD= | C2: 120 | D2: JPY／USD=
B3: ■Balance sheet relating the quotations brought Japanese constructors up by us | Q3: 41844
B5: Item | C5: Contents | D5: Quantity | E5: Unit | F5: ※Company | G5: Chugai Technos Vietnam | H5: Kawaki | I5: Alstom | J5: Mitsubishi | K5: ＩＩＣ | L5: Hitachi | M5: EBARA | N5: Sumitomo | O5: ＭＨＩ solution | Q5: BHIC | R5: BHK
F6: Rule | H6: SV | I6: Measurement | J6: Measurement | K6: Measurement | L6: SV | M6: Measurement | N6: ＳＶ | O6: Measurement | P6: SV | Q6: Measurement | R6: SV
B7: 1．Direct labor cost
C8: Engineering cost | D8: 1 | E8: Nan-hour | H8: =ROUND(H36/$C$2,0) -> 396 | I8: =ROUND(I36/$C$2,0) -> 375 | J8: =ROUND(J36/$C$2,0) -> 333 | K8: =ROUND(K36/$C$2,0) -> 267 | L8: =ROUND(L36/$C$2,0) -> 333 | M8: =ROUND(M36/$C$2,0) -> 333 | N8: =ROUND(N36/$C$2,0) -> 333 | O8: =ROUND(O36/$C$2,0) -> 287 | ... R8: =ROUND(R36/$C$2,0) -> 317
G9: =ROUND(G37/$C$2,0) -> 233 | H9: =$G$9/H8 -> 0.58838384 | I9: =$G$9/I8 -> 0.62133333 | J9: =$G$9/J8 -> 0.6996997 | K9: =$G$9/K8 -> 0.87265918 | L9: =$G$9/L8 -> 0.6996997 | M9: =$G$9/M8 -> 0.6996997 | N9: =$G$9/N8 -> 0.6996997 | O9: =$G$9/O8 -> 0.81184669 | ... R9: =$G$9/R8 -> 0.73501577
G10: =ROUND(G38/$C$2,0) -> 208 | H10: =$G$10/H8 -> 0.52525253 | I10: =$G$10/I8 -> 0.55466667 | J10: =$G$10/J8 -> 0.62462462 | K10: =$G$10/K8 -> 0.77902622 | L10: =$G$10/L8 -> 0.62462462 | M10: =$G$10/M8 -> 0.62462462 | N10: =$G$10/N8 -> 0.62462462 | O10: =$G$10/O8 -> 0.72473868 | ... R10: =$G$10/R8 -> 0.65615142
B12: 2．Direct out-of-pocket cost
C13: ①VISA accession cost | D13: 1 | E13: Times | H13: =ROUND(H41/$C$2,0) -> 285 | J13: =ROUND(J41/$C$2,0) -> 83 | O13: Actual Cost | P13: Actual Cost | Q13: Actual Cost | R13: Actual Cost
C14: ②Daily allowance | D14: 1 | E14: Person・Day | F14: =ROUND(F42/$C$2,0) -> 16 | H14: =ROUND(H42/$C$2,0) -> 42 | I14: =ROUND(I42/$C$2,0) -> 42 | J14: =ROUND(J42/$C$2,0) -> 42 | K14: =ROUND(K42/$C$2,0) -> 42 | L14: =ROUND(L42/$C$2,0) -> 50 | M14: =ROUND(M42/$C$2,0) -> 42 | N14: =ROUND(N42/$C$2,0) -> 42 | O14: =ROUND(O42/$C$2,0) -> 50 | ... R14: =ROUND(R42/$C$2,0) -> 25
C15: ③accommodation cost | D15: 1 | E15: Person・Night | F15: =ROUND(F43/$C$2,0) -> 67 | H15: =ROUND(H43/$C$2,0) -> 90 | I15: =ROUND(I43/$C$2,0) -> 66 | J15: =ROUND(J43/$C$2,0) -> 108 | K15: Actual Cost | L15: =ROUND(L43/$C$2,0) -> 17 | M15: issuance | N15: Actual Cost | O15: Actual Cost | P15: Actual Cost | Q15: Actual Cost | R15: =ROUND(R43/$C$2,0) -> 133
C16: ④Insurance | D16: 1 | E16: Set | H16: =ROUND(H44/$C$2,0) -> 167 | I16: =ROUND(I44/$C$2,0) -> 192 | J16: =ROUND(J44/$C$2,0) -> 100 | K16: =ROUND(K44/$C$2,0) -> 100 | M16: =ROUND(M44/$C$2,0) -> 83 | N16: Actual Cost | O16: Actual Cost | P16: Actual Cost | Q16: Actual Cost | R16: Actual Cost
C17: ⑤Transportation cost | D17: 1 | E17: Set | H17: Actual Cost | I17: Actual Cost | J17: Actual Cost | K17: Actual Cost | L17: Actual Cost | M17: Actual Cost | N17: Actual Cost | O17: Actual Cost | P17: Actual Cost | Q17: Actual Cost | R17: Actual Cost
C18: ⑥Entrance pay | D18: 1 | E18: Set | F18: =ROUND(F46/$C$2,0) -> 83 | J18: =ROUND(J46/$C$2,0) -> 250 | K18: =ROUND(K46/$C$2,0) -> 183 | M18: =ROUND(M46/$C$2,0) -> 167 | N18: =ROUND(N46/$C$2,0) -> 183 | O18: =ROUND(O46/$C$2,0) -> 167 | P18: =ROUND(P46/$C$2,0) -> 167 | Q18: =ROUND(Q46/$C$2,0) -> 300 | R18: =ROUND(R46/$C$2,0) -> 500
C19: ⑦Communication cost | D19: 1 | E19: Set | I19: =ROUND(I47/$C$2,0) -> 125
C20: ⑧Environment addition | D20: 1 | E20: Day | O20: =ROUND(O48/$C$2,0) -> 7 | P20: =ROUND(P48/$C$2,0) -> 7
C21: ⑨Separation allowance | D21: 1 | E21: Day | O21: =ROUND(O49/$C$2,0) -> 8 | P21: =ROUND(P49/$C$2,0) -> 8
C22: ⑩Immunization cost | Q22: Actual Cost | R22: Actual Cost
C23: ⑪Dispatch allowance | D23: 1 | E23: Day | F23: =ROUND(F51/$C$2,0) -> 4
B25: 3．Company cost | G25: 0.15 | H25: 10％ | I25: 10％ | J25: 10％ | K25: 10％ | L25: 15％ | M25: 15％ | N25: 15％ | O25: 10％ | P25: 15％ | Q25: 10％ | R25: 10％
B28: ※In the case that Area is ASEAN （Group C） and employee is regular followed by company rule
B31: ■国内プラントメーカー提出見積の比較 | Q31: 41479
B33: 項 目 | C33: 内 容 | D33: 数量 | E33: 単位 | F33: 会社※ | G33: 中外 ベトナム | H33: 川重 | I33: アルストム | J33: 三菱 | K33: ＩＩＣ | L33: 日立プラント | M33: 荏原環境Ｐ | N33: 住重 | O33: ＭＨＩｿﾘｭｰｼｮﾝ | Q33: BHIC | R33: BHK
F34: 規定 | H34: ＳＶ | I34: 計測 | J34: 計測 | K34: 計測 | L34: ＳＶ | M34: 計測 | N34: ＳＶ | O34: 計測 | P34: ＳＶ | Q34: 計測 | R34: ＳＶ
B35: １．直接人件費
C36: 技術料 | D36: 1 | E36: 人工 | H36: 47500 | I36: 45040 | J36: 40000 | K36: 32000 | L36: 40000 | M36: 40000 | N36: 40000 | O36: 34400 | P36: 38400 | Q36: 22800 | R36: 38000
G37: 28000 | H37: =$G$9/H36 -> 0.0049052632 | I37: =$G$9/I36 -> 0.0051731794 | J37: =$G$9/J36 -> 0.005825 | K37: =$G$9/K36 -> 0.00728125 | L37: =$G$9/L36 -> 0.005825 | M37: =$G$9/M36 -> 0.005825 | N37: =$G$9/N36 -> 0.005825 | O37: =$G$9/O36 -> 0.0067732558 | ... R37: =$G$9/R36 -> 0.0061315789
G38: 25000 | H38: =$G$10/H36 -> 0.0043789474 | I38: =$G$10/I36 -> 0.0046181172 | J38: =$G$10/J36 -> 0.0052 | K38: =$G$10/K36 -> 0.0065 | L38: =$G$10/L36 -> 0.0052 | M38: =$G$10/M36 -> 0.0052 | N38: =$G$10/N36 -> 0.0052 | O38: =$G$10/O36 -> 0.0060465116 | ... R38: =$G$10/R36 -> 0.0054736842
B40: 2．直接経費
C41: ①ビザ取得費等 | D41: 1 | E41: 回 | H41: 34150 | J41: 10000 | O41: 実費 | P41: 実費 | Q41: 実費 | R41: 実費
C42: ②日当 | D42: 1 | E42: 人・日 | F42: 1900 | H42: 5000 | I42: 5000 | J42: 5000 | K42: 5000 | L42: 6000 | M42: 5000 | N42: 5000 | O42: 6000 | P42: 6000 | Q42: 5000 | R42: 3000
C43: ③宿泊費 | D43: 1 | E43: 人・泊 | F43: 8000 | H43: 10750 | I43: 7880 | J43: 13000 | K43: 実費 | L43: 2000 | M43: 支給 | N43: 実費 | O43: 実費 | P43: 実費 | Q43: 実費 | R43: 16000
C44: ④保険料 | D44: 1 | E44: 式 | H44: 20000 | I44: 23000 | J44: 12000 | K44: 12000 | M44: 10000 | N44: 実費 | O44: 実費 | P44: 実費 | Q44: 実費 | R44: 実費
C45: ⑤交通費 | D45: 1 | E45: 式 | H45: 実費 | I45: 実費 | J45: 実費 | K45: 実費 | L45: 実費 | M45: 実費 | N45: 実費 | O45: 実費 | P45: 実費 | Q45: 実費 | R45: 実費
C46: ⑥支度金 | D46: 1 | E46: 式 | F46: 10000 | J46: 30000 | K46: 22000 | M46: 20000 | N46: 22000 | O46: 20000 | P46: 20000 | Q46: 36000 | R46: 60000
C47: ⑦通信費 | D47: 1 | E47: 式 | I47: 15000
C48: ⑧環境加算 | D48: 1 | E48: 日 | O48: 800 | P48: 800
C49: ⑨別居手当 | D49: 1 | E49: 日 | O49: 1000 | P49: 1000
C50: ⑩予防注射代 | Q50: 実費 | R50: 実費
C51: ⑪派遣手当 | D51: 1 | E51: 日 | F51: 500
B53: ３．会社経費 | G53: 0.15 | H53: １０％ | I53: １０％ | J53: １０％ | K53: １０％ | L53: １５％ | M53: １５％ | N53: １５％ | O53: １０％ | P53: １５％ | Q53: １０％ | R53: １０％
B56: ※会社規定は、ASEANエリア（Ｃ地区）、一般とする。
